aggregationslib/__init__.py
aggregationslib/aggregation.py
aggregationslib/aggregations.py
aggregationslib/decimalaggregations.py
aggregationslib/example.py
aggregationslib/purepython.py
aggregationslib/conjuctive/__init__.py
aggregationslib/conjuctive/purepython.py
aggregationslib/disjunctive/__init__.py
aggregationslib-0.1.4.dist-info/LICENSE
aggregationslib-0.1.4.dist-info/METADATA
aggregationslib-0.1.4.dist-info/WHEEL
aggregationslib-0.1.4.dist-info/top_level.txt
aggregationslib-0.1.4.dist-info/RECORD
