Metadata-Version: 2.2
Name: aggregationslib
Version: 0.1.4
Summary: Python implementation of Arithmetic, quasi arithmetic and other aggregating functions
Author: wgalka
Project-URL: Homepage, https://github.com/wgalka/Means
Project-URL: Download, https://github.com/wgalka/Means/releases/latest
Classifier: Programming Language :: Python :: 3.13
Classifier: Operating System :: OS Independent
Requires-Python: >=3.12
License-File: LICENSE
Requires-Dist: numpy>=2.2.2
Requires-Dist: pynverse
Provides-Extra: test
Requires-Dist: pytest>=8.3.4; extra == "test"
